TerminalGameTools.py
TerminalGameTools-0.0.3.dist-info/LICENSE
TerminalGameTools-0.0.3.dist-info/METADATA
TerminalGameTools-0.0.3.dist-info/WHEEL
TerminalGameTools-0.0.3.dist-info/top_level.txt
TerminalGameTools-0.0.3.dist-info/RECORD
